data_processing/__init__.py
data_processing/comparison.py
data_processing/duplicate_handling.py
data_processing/modification.py
data_processing/sorting.py
brrrDataProcessor-0.1.0.dist-info/METADATA
brrrDataProcessor-0.1.0.dist-info/WHEEL
brrrDataProcessor-0.1.0.dist-info/entry_points.txt
brrrDataProcessor-0.1.0.dist-info/top_level.txt
brrrDataProcessor-0.1.0.dist-info/RECORD
