Metadata-Version: 2.1
Name: brrrDataProcessor
Version: 0.1.0
Summary: A data processing tool for Excel files
Home-page: https://github.com/felix-arvidsson/brrrDataProcessor/
Author: Felix Arvidsson
Author-email: felix.arvidsson@gmail.com
Classifier: Programming Language :: Python :: 3
Classifier: License :: OSI Approved :: MIT License
Classifier: Operating System :: OS Independent
Requires-Dist: blessed==1.20.0
Requires-Dist: editor==1.6.6
Requires-Dist: et-xmlfile==1.1.0
Requires-Dist: inquirer==3.4.0
Requires-Dist: numpy==2.1.1
Requires-Dist: openpyxl==3.1.5
Requires-Dist: pandas==2.2.2
Requires-Dist: prompt-toolkit==3.0.47
Requires-Dist: python-dateutil==2.9.0.post0
Requires-Dist: pytz==2024.1
Requires-Dist: readchar==4.2.0
Requires-Dist: runs==1.2.2
Requires-Dist: six==1.16.0
Requires-Dist: tzdata==2024.1
Requires-Dist: wcwidth==0.2.13
Requires-Dist: xmod==1.8.1
